git_project/__init__.py
git_project/lists/__init__.py
git_project/methods/__init__.py
git_project/methods/add_student.py
git_project/methods/attendance.py
git_project/methods/export_students.py
git_project/methods/import_students.py
git_project/methods/main.py
unit_tests/__init__.py
unit_tests/test_add_export_student.py
unit_tests/test_attendance.py
unit_tests/test_import.py
SON_ZAD2_tests-1.1.2.dist-info/METADATA
SON_ZAD2_tests-1.1.2.dist-info/WHEEL
SON_ZAD2_tests-1.1.2.dist-info/top_level.txt
SON_ZAD2_tests-1.1.2.dist-info/RECORD
