Metadata-Version: 2.1
Name: SON_ZAD2-tests
Version: 1.1.2
Summary: Attendance project
Home-page: https://github.com/SheoTM/SON_ZAD2-tests
Classifier: Programming Language :: Python :: 3
Requires-Python: >=3.12
Requires-Dist: annotated-types==0.7.0
Requires-Dist: anyio==4.6.2.post1
Requires-Dist: certifi==2024.8.30
Requires-Dist: charset-normalizer==3.4.0
Requires-Dist: click==8.1.7
Requires-Dist: coverage==7.6.4
Requires-Dist: dnspython==2.7.0
Requires-Dist: docutils==0.21.2
Requires-Dist: email-validator==2.2.0
Requires-Dist: fastapi==0.115.4
Requires-Dist: fastapi-cli==0.0.5
Requires-Dist: h11==0.14.0
Requires-Dist: httpcore==1.0.6
Requires-Dist: httptools==0.6.4
Requires-Dist: httpx==0.27.2
Requires-Dist: idna==3.10
Requires-Dist: importlib-metadata==8.5.0
Requires-Dist: iniconfig==2.0.0
Requires-Dist: jaraco.classes==3.4.0
Requires-Dist: jaraco.context==6.0.1
Requires-Dist: jaraco.functools==4.1.0
Requires-Dist: Jinja2==3.1.4
Requires-Dist: keyring==25.5.0
Requires-Dist: markdown-it-py==3.0.0
Requires-Dist: MarkupSafe==3.0.2
Requires-Dist: mdurl==0.1.2
Requires-Dist: more-itertools==10.5.0
Requires-Dist: nh3==0.2.18
Requires-Dist: packaging==24.2
Requires-Dist: pkginfo==1.10.0
Requires-Dist: pluggy==1.5.0
Requires-Dist: pydantic==2.9.2
Requires-Dist: pydantic-core==2.23.4
Requires-Dist: Pygments==2.18.0
Requires-Dist: pytest==8.3.3
Requires-Dist: pytest-cov==6.0.0
Requires-Dist: python-dotenv==1.0.1
Requires-Dist: python-multipart==0.0.17
Requires-Dist: PyYAML==6.0.2
Requires-Dist: readme-renderer==44.0
Requires-Dist: requests==2.32.3
Requires-Dist: requests-toolbelt==1.0.0
Requires-Dist: rfc3986==2.0.0
Requires-Dist: rich==13.9.4
Requires-Dist: setuptools==75.5.0
Requires-Dist: shellingham==1.5.4
Requires-Dist: sniffio==1.3.1
Requires-Dist: SQLAlchemy==2.0.36
Requires-Dist: sqlmodel==0.0.22
Requires-Dist: starlette==0.41.2
Requires-Dist: twine==5.1.1
Requires-Dist: typer==0.13.0
Requires-Dist: typing-extensions==4.12.2
Requires-Dist: urllib3==2.2.3
Requires-Dist: uvicorn==0.32.0
Requires-Dist: watchfiles==0.24.0
Requires-Dist: websockets==14.0
Requires-Dist: wheel==0.45.0
Requires-Dist: zipp==3.21.0
